invexpo/__init__.py
invexpo/exceptions.py
invexpo/inverse_exponential.py
invexpo-0.1.2.dist-info/METADATA
invexpo-0.1.2.dist-info/WHEEL
invexpo-0.1.2.dist-info/licenses/LICENSE
invexpo-0.1.2.dist-info/RECORD
